ibpmodel/SW_OPER_IBP_CLI_2__00000000T000000_99999999T999999_0004.cdf
ibpmodel/__init__.py
ibpmodel/ibpcalc.py
ibpmodel/ibpforward.py
ibpmodel-1.4.2.dist-info/licenses/LICENSE
ibpmodel-1.4.2.dist-info/METADATA
ibpmodel-1.4.2.dist-info/WHEEL
ibpmodel-1.4.2.dist-info/top_level.txt
ibpmodel-1.4.2.dist-info/RECORD
