Metadata-Version: 2.4
Name: ibpmodel
Version: 1.4.2
Summary: Ionospheric Bubble Probability
Author: Martin Rother
Maintainer-email: Ina Rusch <rusch@iap-kborn.de>
License: MIT License
Project-URL: homepage, https://igit.iap-kborn.de/ibp/ibp-model.git
Project-URL: documentation, https://ibp-model.readthedocs.io
Project-URL: repository, https://igit.iap-kborn.de/ibp/ibp-model.git
Project-URL: changelog, https://igit.iap-kborn.de/ibp/ibp-model/-/raw/main/CHANGELOG.rst
Classifier: Development Status :: 5 - Production/Stable
Classifier: Intended Audience :: Science/Research
Classifier: License :: OSI Approved :: MIT License
Classifier: Programming Language :: Python :: 3
Classifier: Programming Language :: Python :: 3.8
Classifier: Programming Language :: Python :: 3.9
Classifier: Programming Language :: Python :: 3.10
Classifier: Programming Language :: Python :: 3.11
Classifier: Programming Language :: Python :: 3.12
Classifier: Operating System :: Unix
Classifier: Operating System :: Microsoft :: Windows
Classifier: Operating System :: MacOS
Classifier: Topic :: Scientific/Engineering :: Physics
Classifier: Topic :: Scientific/Engineering :: Atmospheric Science
Requires-Python: >=3.8
License-File: LICENSE
Requires-Dist: numpy>=1.18
Requires-Dist: cdflib>=0.3.5
Requires-Dist: scipy>=1.4
Requires-Dist: pandas>=1.4
Requires-Dist: matplotlib>=2.2
Dynamic: license-file
